bhmsh/__init__.py
bhmsh/__main__.py
bhmsh/bhmsh.py
bhmsh-1.1.3.dist-info/LICENSE
bhmsh-1.1.3.dist-info/METADATA
bhmsh-1.1.3.dist-info/WHEEL
bhmsh-1.1.3.dist-info/entry_points.txt
bhmsh-1.1.3.dist-info/top_level.txt
bhmsh-1.1.3.dist-info/RECORD
