Metadata-Version: 2.1
Name: bhmsh
Version: 1.1.3
Summary: A lightweight OpenAI-powered Bash actuator.
Author-email: Collin Hinson <collin@bizhandyman.com>
Project-URL: Homepage, https://github.com/Business-Handyman-LLC/bhm-sh
Project-URL: Bug Tracker, https://github.com/Business-Handyman-LLC/bhm-sh/issues
Classifier: Programming Language :: Python :: 3
Classifier: License :: OSI Approved :: MIT License
Classifier: Operating System :: OS Independent
Requires-Python: >=3.8
License-File: LICENSE
Requires-Dist: openai >=0.28.1
